[
    {
        "site" : "yandex",
        "link" : "http://feeds.feedburner.com/yandex/MAOo",
        "type" : "rss"
    },
    {
        "site" : "kommersant",
        "link" : "http://www.kommersant.ru/RSS/news.xml",
        "type" : "rss"
    },
    {
        "site" : "ria",
        "link" : "http://www.rian.ru/export/rss2/index.xml",
        "type" : "rss"
    },
    {
        "site" : "vz",
        "link" : "http://www.vz.ru/export/yandex.xml",
        "type" : "rss"
    },
    {
        "site" : "habr",
        "link" : "http://www.habrahabr.ru/rss/main/",
        "type" : "rss"
    },
    {
        "site" : "vz",
        "link" : "http://www.vz.ru/export/yandex.xml",
        "type" : "rss"
    },
    {
        "site" : "cnn",
        "link" : "http://rss.cnn.com/rss/cnn_world.rss",
        "type" : "rss"
    }
]